{
  "minecraft:recipes/decorations/crafting_table": {
    "criteria": {
      "unlock_right_away": "2024-02-29 11:32:54 +0100"
    },
    "done": true
  },
  "minecraft:adventure/adventuring_time": {
    "criteria": {
      "minecraft:beach": "2024-02-29 11:32:59 +0100",
      "minecraft:cold_ocean": "2024-02-29 11:33:06 +0100",
      "minecraft:forest": "2024-02-29 11:33:08 +0100"
    },
    "done": false
  },
  "minecraft:recipes/misc/iron_nugget_from_smelting": {
    "criteria": {
      "has_iron_shovel": "2024-02-29 11:33:59 +0100"
    },
    "done": true
  },
  "minecraft:recipes/misc/iron_nugget_from_blasting": {
    "criteria": {
      "has_iron_shovel": "2024-02-29 11:33:59 +0100"
    },
    "done": true
  },
  "minecraft:recipes/misc/gold_nugget_from_smelting": {
    "criteria": {
      "has_golden_shovel": "2024-02-29 11:34:01 +0100"
    },
    "done": true
  },
  "minecraft:recipes/misc/gold_nugget_from_blasting": {
    "criteria": {
      "has_golden_shovel": "2024-02-29 11:34:01 +0100"
    },
    "done": true
  },
  "minecraft:recipes/transportation/mangrove_boat": {
    "criteria": {
      "in_water": "2024-02-29 11:43:16 +0100"
    },
    "done": true
  },
  "minecraft:recipes/transportation/acacia_boat": {
    "criteria": {
      "in_water": "2024-02-29 11:43:16 +0100"
    },
    "done": true
  },
  "minecraft:recipes/transportation/cherry_boat": {
    "criteria": {
      "in_water": "2024-02-29 11:43:16 +0100"
    },
    "done": true
  },
  "minecraft:recipes/transportation/bamboo_raft": {
    "criteria": {
      "in_water": "2024-02-29 11:43:16 +0100"
    },
    "done": true
  },
  "minecraft:recipes/transportation/spruce_boat": {
    "criteria": {
      "in_water": "2024-02-29 11:43:16 +0100"
    },
    "done": true
  },
  "minecraft:recipes/transportation/birch_boat": {
    "criteria": {
      "in_water": "2024-02-29 11:43:16 +0100"
    },
    "done": true
  },
  "minecraft:recipes/transportation/oak_boat": {
    "criteria": {
      "in_water": "2024-02-29 11:43:16 +0100"
    },
    "done": true
  },
  "minecraft:recipes/transportation/jungle_boat": {
    "criteria": {
      "in_water": "2024-02-29 11:43:16 +0100"
    },
    "done": true
  },
  "minecraft:recipes/transportation/dark_oak_boat": {
    "criteria": {
      "in_water": "2024-02-29 11:43:16 +0100"
    },
    "done": true
  },
  "minecraft:recipes/decorations/painting": {
    "criteria": {
      "has_wool": "2024-03-01 09:32:50 +0100"
    },
    "done": true
  },
  "minecraft:recipes/decorations/pink_bed": {
    "criteria": {
      "has_pink_wool": "2024-03-01 09:32:50 +0100"
    },
    "done": true
  },
  "minecraft:recipes/decorations/pink_carpet": {
    "criteria": {
      "has_pink_wool": "2024-03-01 09:32:50 +0100"
    },
    "done": true
  },
  "minecraft:recipes/decorations/pink_banner": {
    "criteria": {
      "has_pink_wool": "2024-03-01 09:32:50 +0100"
    },
    "done": true
  },
  "minecraft:recipes/decorations/chest": {
    "criteria": {
      "has_lots_of_items": "2024-03-01 12:43:15 +0100"
    },
    "done": true
  },
  "minecraft:adventure/root": {
    "criteria": {
      "killed_something": "2024-03-01 12:43:15 +0100"
    },
    "done": true
  },
  "minecraft:adventure/kill_all_mobs": {
    "criteria": {
      "minecraft:creeper": "2024-03-01 12:43:15 +0100"
    },
    "done": false
  },
  "minecraft:adventure/kill_a_mob": {
    "criteria": {
      "minecraft:creeper": "2024-03-01 12:43:15 +0100"
    },
    "done": true
  },
  "minecraft:recipes/misc/firework_rocket_simple": {
    "criteria": {
      "has_gunpowder": "2024-03-01 12:43:15 +0100"
    },
    "done": true
  },
  "minecraft:recipes/redstone/tnt": {
    "criteria": {
      "has_gunpowder": "2024-03-01 12:43:15 +0100"
    },
    "done": true
  },
  "minecraft:husbandry/root": {
    "criteria": {
      "consumed_item": "2024-03-01 12:44:06 +0100"
    },
    "done": true
  },
  "minecraft:husbandry/obtain_netherite_hoe": {
    "criteria": {
      "netherite_hoe": "2024-03-01 13:10:22 +0100"
    },
    "done": true
  },
  "minecraft:recipes/brewing/cauldron": {
    "criteria": {
      "has_water_bucket": "2024-03-01 13:10:24 +0100"
    },
    "done": true
  },
  "minecraft:husbandry/plant_seed": {
    "criteria": {
      "melon_stem": "2024-03-01 13:10:33 +0100"
    },
    "done": true
  },
  "minecraft:recipes/misc/white_dye": {
    "criteria": {
      "has_bone_meal": "2024-03-01 13:10:40 +0100"
    },
    "done": true
  },
  "minecraft:recipes/building_blocks/bone_block": {
    "criteria": {
      "has_bone_meal": "2024-03-01 13:10:40 +0100"
    },
    "done": true
  },
  "minecraft:recipes/decorations/smoker": {
    "criteria": {
      "has_furnace": "2024-03-04 11:19:04 +0100"
    },
    "done": true
  },
  "minecraft:recipes/misc/iron_ingot_from_smelting_iron_ore": {
    "criteria": {
      "has_iron_ore": "2024-03-04 11:19:11 +0100"
    },
    "done": true
  },
  "minecraft:recipes/misc/iron_ingot_from_blasting_iron_ore": {
    "criteria": {
      "has_iron_ore": "2024-03-04 11:19:11 +0100"
    },
    "done": true
  },
  "wonderland_mod_id:recipes/misc/chocolate_item_from_smelting_chocolate_item": {
    "criteria": {
      "has_chocolate_item": "2024-03-04 16:12:25 +0100"
    },
    "done": true
  },
  "wonderland_mod_id:recipes/misc/chocolate_item": {
    "criteria": {
      "has_chocolate_block": "2024-03-04 16:10:59 +0100"
    },
    "done": true
  },
  "wonderland_mod_id:recipes/misc/chocolate_block": {
    "criteria": {
      "has_chocolate_item": "2024-03-04 16:12:25 +0100"
    },
    "done": true
  },
  "wonderland_mod_id:recipes/misc/chocolate_item_from_blasting_chocolate_item": {
    "criteria": {
      "has_chocolate_item": "2024-03-04 16:12:25 +0100"
    },
    "done": true
  },
  "DataVersion": 3465
}